staticscraper/__init__.py
staticscraper/staticscraper.py
keywind_staticscraper-2.3.0.dist-info/LICENSE
keywind_staticscraper-2.3.0.dist-info/METADATA
keywind_staticscraper-2.3.0.dist-info/WHEEL
keywind_staticscraper-2.3.0.dist-info/top_level.txt
keywind_staticscraper-2.3.0.dist-info/RECORD
