Metadata-Version: 2.1
Name: keywind-staticscraper
Version: 2.3.0
Summary: Installing this package will allow you to scrape webpages.
Home-page: https://github.com/keywind1207/keywind-staticscraper
Author: Keywind
Author-email: keywind127@gmail.com
License: UNKNOWN
Project-URL: Bug Tracker, https://github.com/keywind1207/keywind-staticscraper/issues
Platform: UNKNOWN
Classifier: Programming Language :: Python :: 3
Classifier: License :: OSI Approved :: MIT License
Classifier: Operating System :: OS Independent
Requires-Python: >=3.6
License-File: LICENSE
Requires-Dist: markdown
Requires-Dist: bs4
Requires-Dist: lxml
Requires-Dist: requests
Requires-Dist: pandas
Requires-Dist: selenium
